waimoku/__init__.py
waimoku/client.py
waimoku/main.py
waimoku/setsuei_status.py
waimoku/user.py
waimoku/user_list_provider.py
waimoku/waimoku.py
waimoku/res/event_visitorList.xlsx
waimoku-0.0.9.dist-info/LICENSE
waimoku-0.0.9.dist-info/METADATA
waimoku-0.0.9.dist-info/WHEEL
waimoku-0.0.9.dist-info/entry_points.txt
waimoku-0.0.9.dist-info/top_level.txt
waimoku-0.0.9.dist-info/RECORD
