Metadata-Version: 2.1
Name: waimoku
Version: 0.0.9
Summary: ワイもくのConnpasで取得しているアンケートから運営に必要な情報を抽出するPythonのScript です。
Home-page: UNKNOWN
Author: Atsuki Seo
Maintainer: Atsuki Seo
License: MIT
Platform: UNKNOWN
Classifier: Programming Language :: Python :: 3.7
Classifier: License :: OSI Approved :: MIT License
Requires-Dist: pandas
Requires-Dist: openpyxl
